dnswait.py
dnswait-0.0.1.dist-info/METADATA
dnswait-0.0.1.dist-info/WHEEL
dnswait-0.0.1.dist-info/entry_points.txt
dnswait-0.0.1.dist-info/top_level.txt
dnswait-0.0.1.dist-info/RECORD
