Metadata-Version: 2.1
Name: dnswait
Version: 0.0.1
Summary: attr: dnswait.__doc__
Home-page: https://github.com/JulienPalard/dnswait
Author: Julien Palard
Author-email: julien@palard.fr
License: MIT License
Platform: UNKNOWN
Classifier: Development Status :: 5 - Production/Stable
Classifier: Intended Audience :: Developers
Classifier: License :: OSI Approved :: MIT License
Requires-Python: >=3.6
Requires-Dist: dnspython
